pydantic_ai_langfuse/__init__.py
pydantic_ai_langfuse/models.py
pydantic_ai_langfuse-0.1.2.dist-info/LICENSE
pydantic_ai_langfuse-0.1.2.dist-info/METADATA
pydantic_ai_langfuse-0.1.2.dist-info/WHEEL
pydantic_ai_langfuse-0.1.2.dist-info/RECORD
