Metadata-Version: 2.1
Name: pydantic-ai-langfuse
Version: 0.1.2
Summary: Langfuse integration for pydantic-ai
License: MIT
Author: Gabriele Ghisleni
Author-email: gabriele.ghisleni01@gmail.com
Requires-Python: >=3.10,<4.0
Classifier: License :: OSI Approved :: MIT License
Classifier: Programming Language :: Python :: 3
Classifier: Programming Language :: Python :: 3.10
Classifier: Programming Language :: Python :: 3.11
Classifier: Programming Language :: Python :: 3.12
Requires-Dist: langfuse[openai] (>=2.58.2,<3.0.0)
Requires-Dist: pydantic-ai-slim[openai] (>=0.0.21,<0.0.22)
